{
    "dependencies": [
        {
            "path": "primitives.filesystem",
            "range": "master"
        },
        {
            "path": "primitives.templates",
            "range": "master"
        },
        {
            "path": "org.sw.demo.imageworks.pystring",
            "range": ">=1.0.0 <2.0.0"
        }
    ],
    "path": "org.sw.demo.primitives.db.common",
    "source": {
        "git": {
            "branch": "{v}",
            "url": "https://github.com/egorpugin/primitives"
        }
    },
    "version": "master"
}