{
    "dependencies": [
        {
            "path": "boost.assert",
            "versions": "develop"
        },
        {
            "path": "boost.config",
            "versions": "develop"
        },
        {
            "path": "boost.core",
            "versions": "develop"
        },
        {
            "path": "boost.predef",
            "versions": "develop"
        },
        {
            "path": "boost.winapi",
            "versions": "develop"
        }
    ],
    "path": "org.sw.demo.boost.system",
    "source": {
        "git": {
            "branch": "{v}",
            "url": "https://github.com/boostorg/system"
        }
    },
    "version": "develop"
}